README.rst
setup.py
mlfs/__init__.py
mlfs.egg-info/PKG-INFO
mlfs.egg-info/SOURCES.txt
mlfs.egg-info/dependency_links.txt
mlfs.egg-info/top_level.txt