Metadata-Version: 1.1
Name: mlfs
Version: 0.1.1
Summary: A package for maximum likelihood density fitting and simulation.
Home-page: https://github.com/romanov360/mlfs
Author: Tristan Romanov
Author-email: romanov360@gmail.com
License: BSD 2-clause
Platform: UNKNOWN
Classifier: Development Status :: 1 - Planning
Classifier: Intended Audience :: Science/Research
Classifier: License :: OSI Approved :: BSD License
Classifier: Operating System :: OS Independent
Classifier: Programming Language :: Python
